featureexpand/__init__.py
featureexpand/_init_.py
featureexpand/feature_expander.py
featureexpand/improver.py
featureexpand/neural.py
featureexpand/utils.py
featureexpand-0.4.0.dist-info/LICENSE
featureexpand-0.4.0.dist-info/METADATA
featureexpand-0.4.0.dist-info/WHEEL
featureexpand-0.4.0.dist-info/top_level.txt
featureexpand-0.4.0.dist-info/RECORD
