Metadata-Version: 2.1
Name: featureexpand
Version: 0.4.0
Summary: A powerful Python library for automatic feature engineering using logical formula simplification
Home-page: https://gitlab.com/exactor/featureexpand.git
Author: Juan Carlos Lopez Gonzalez
Author-email: Juan Carlos Lopez Gonzalez <jlopez1967@gmail.com>
License: MIT
Project-URL: Homepage, https://gitlab.com/exactor/featureexpand.git
Project-URL: Documentation, https://featureexpand.readthedocs.io
Project-URL: Repository, https://gitlab.com/exactor/featureexpand.git
Project-URL: Bug Tracker, https://gitlab.com/exactor/featureexpand.git/issues
Keywords: machine-learning,feature-engineering,boolean-logic,optimization,scikit-learn
Classifier: Development Status :: 4 - Beta
Classifier: Intended Audience :: Developers
Classifier: Intended Audience :: Science/Research
Classifier: License :: OSI Approved :: MIT License
Classifier: Operating System :: OS Independent
Classifier: Programming Language :: Python :: 3
Classifier: Programming Language :: Python :: 3.8
Classifier: Programming Language :: Python :: 3.9
Classifier: Programming Language :: Python :: 3.10
Classifier: Programming Language :: Python :: 3.11
Classifier: Topic :: Scientific/Engineering :: Artificial Intelligence
Classifier: Topic :: Software Development :: Libraries :: Python Modules
Requires-Python: >=3.8
License-File: LICENSE
Requires-Dist: numpy>=1.19.0
Requires-Dist: pandas>=1.1.0
Requires-Dist: scikit-learn>=0.24.0
Requires-Dist: requests>=2.25.0
Provides-Extra: dev
Requires-Dist: pytest>=7.0.0; extra == "dev"
Requires-Dist: pytest-cov>=3.0.0; extra == "dev"
Requires-Dist: black>=22.0.0; extra == "dev"
Requires-Dist: flake8>=4.0.0; extra == "dev"
Requires-Dist: mypy>=0.950; extra == "dev"
Requires-Dist: build>=0.8.0; extra == "dev"
Requires-Dist: twine>=4.0.0; extra == "dev"
Provides-Extra: docs
Requires-Dist: mkdocs>=1.4.0; extra == "docs"
Requires-Dist: mkdocs-material>=8.5.0; extra == "docs"
Requires-Dist: mkdocstrings[python]>=0.19.0; extra == "docs"
